{
    "audioUrl": [
        "src/music/music00009.mp3"
    ],
    "images": [
        "src/images/reel.jpg"
    ],
    "words": [
        {
            "word": "Technology.",
            "start": 0,
            "end": 1.08,
            "confidence": "0.9686077",
            "punctuated_word": "Technology."
        },
        {
            "word": ".",
            "start": 1.4,
            "end": 1.68,
            "confidence": "0.9549275",
            "punctuated_word": "."
        },
        {
            "word": ".",
            "start": 2,
            "end": 2.28,
            "confidence": "0.9412324",
            "punctuated_word": "."
        },
        {
            "word": "technology",
            "start": 2.6,
            "end": 3.6,
            "confidence": "0.9640442",
            "punctuated_word": "technology"
        },
        {
            "word": "never",
            "start": 3.62,
            "end": 4.22,
            "confidence": "0.9721267",
            "punctuated_word": "never"
        },
        {
            "word": "changes!",
            "start": 4.24,
            "end": 5.08,
            "confidence": "0.9225879",
            "punctuated_word": "changes!"
        },
        {
            "word": "-",
            "start": 5.4,
            "end": 5.68,
            "confidence": "0.9512725",
            "punctuated_word": "-"
        },
        {
            "word": "or",
            "start": 5.7,
            "end": 6.06,
            "confidence": "0.9884344",
            "punctuated_word": "or"
        },
        {
            "word": "does",
            "start": 6.08,
            "end": 6.6,
            "confidence": "0.9458803",
            "punctuated_word": "does"
        },
        {
            "word": "it?",
            "start": 6.62,
            "end": 7.06,
            "confidence": "0.9819665",
            "punctuated_word": "it?"
        },
        {
            "word": "How",
            "start": 7.38,
            "end": 7.82,
            "confidence": "0.9647457",
            "punctuated_word": "How"
        },
        {
            "word": "I",
            "start": 7.84,
            "end": 8.12,
            "confidence": "0.9607702",
            "punctuated_word": "I"
        },
        {
            "word": "created",
            "start": 8.14,
            "end": 8.9,
            "confidence": "0.9479196",
            "punctuated_word": "created"
        },
        {
            "word": "a",
            "start": 8.92,
            "end": 9.2,
            "confidence": "0.9810268",
            "punctuated_word": "a"
        },
        {
            "word": "smart",
            "start": 9.22,
            "end": 9.82,
            "confidence": "0.9413702",
            "punctuated_word": "smart"
        },
        {
            "word": "home",
            "start": 9.84,
            "end": 10.36,
            "confidence": "0.9477669",
            "punctuated_word": "home"
        },
        {
            "word": "dashboard",
            "start": 10.38,
            "end": 11.3,
            "confidence": "0.9290172",
            "punctuated_word": "dashboard"
        },
        {
            "word": "on",
            "start": 11.32,
            "end": 11.68,
            "confidence": "0.9395290",
            "punctuated_word": "on"
        },
        {
            "word": "an",
            "start": 11.7,
            "end": 12.06,
            "confidence": "0.9421246",
            "punctuated_word": "an"
        },
        {
            "word": "old",
            "start": 12.08,
            "end": 12.52,
            "confidence": "0.9788378",
            "punctuated_word": "old"
        },
        {
            "word": "jailbroken",
            "start": 12.54,
            "end": 13.54,
            "confidence": "0.9355740",
            "punctuated_word": "jailbroken"
        },
        {
            "word": "Kindle",
            "start": 13.56,
            "end": 14.24,
            "confidence": "0.9272189",
            "punctuated_word": "Kindle"
        },
        {
            "word": "4",
            "start": 14.26,
            "end": 14.54,
            "confidence": "0.9683854",
            "punctuated_word": "4"
        },
        {
            "word": "Touch",
            "start": 14.56,
            "end": 15.16,
            "confidence": "0.9423200",
            "punctuated_word": "Touch"
        },
        {
            "word": "using",
            "start": 15.18,
            "end": 15.78,
            "confidence": "0.9988216",
            "punctuated_word": "using"
        },
        {
            "word": "HTML,",
            "start": 15.8,
            "end": 16.4,
            "confidence": "0.9646607",
            "punctuated_word": "HTML,"
        },
        {
            "word": "PHP,",
            "start": 16.42,
            "end": 16.94,
            "confidence": "0.9505701",
            "punctuated_word": "PHP,"
        },
        {
            "word": "CSS,",
            "start": 16.96,
            "end": 17.48,
            "confidence": "0.9262076",
            "punctuated_word": "CSS,"
        },
        {
            "word": "and",
            "start": 17.5,
            "end": 17.94,
            "confidence": "0.9693345",
            "punctuated_word": "and"
        },
        {
            "word": "JavaScript.",
            "start": 17.96,
            "end": 19.04,
            "confidence": "0.9295470",
            "punctuated_word": "JavaScript."
        },
        {
            "word": "A",
            "start": 19.36,
            "end": 19.64,
            "confidence": "0.9162976",
            "punctuated_word": "A"
        },
        {
            "word": "simple",
            "start": 19.66,
            "end": 20.34,
            "confidence": "0.9885191",
            "punctuated_word": "simple"
        },
        {
            "word": "tutorial",
            "start": 20.36,
            "end": 21.2,
            "confidence": "0.9106405",
            "punctuated_word": "tutorial"
        },
        {
            "word": "from",
            "start": 21.22,
            "end": 21.74,
            "confidence": "0.9969563",
            "punctuated_word": "from"
        },
        {
            "word": "jailbreaking",
            "start": 21.76,
            "end": 22.92,
            "confidence": "0.9470350",
            "punctuated_word": "jailbreaking"
        },
        {
            "word": "to",
            "start": 22.94,
            "end": 23.3,
            "confidence": "0.9120515",
            "punctuated_word": "to"
        },
        {
            "word": "the",
            "start": 23.32,
            "end": 23.76,
            "confidence": "0.9424163",
            "punctuated_word": "the"
        },
        {
            "word": "finished",
            "start": 23.78,
            "end": 24.62,
            "confidence": "0.9229263",
            "punctuated_word": "finished"
        },
        {
            "word": "dashboard.",
            "start": 24.64,
            "end": 25.64,
            "confidence": "0.9656940",
            "punctuated_word": "dashboard."
        },
        {
            "word": "Schau",
            "start": 25.96,
            "end": 26.56,
            "confidence": "0.9838824",
            "punctuated_word": "Schau"
        },
        {
            "word": "auf",
            "start": 26.58,
            "end": 27.02,
            "confidence": "0.9815911",
            "punctuated_word": "auf"
        },
        {
            "word": "meinen",
            "start": 27.04,
            "end": 27.72,
            "confidence": "0.9613156",
            "punctuated_word": "meinen"
        },
        {
            "word": "Blog,",
            "start": 27.74,
            "end": 28.34,
            "confidence": "0.9223661",
            "punctuated_word": "Blog,"
        },
        {
            "word": "um",
            "start": 28.36,
            "end": 28.72,
            "confidence": "0.9721251",
            "punctuated_word": "um"
        },
        {
            "word": "mehr",
            "start": 28.74,
            "end": 29.26,
            "confidence": "0.9849681",
            "punctuated_word": "mehr"
        },
        {
            "word": "zu",
            "start": 29.28,
            "end": 29.64,
            "confidence": "0.9427682",
            "punctuated_word": "zu"
        },
        {
            "word": "erfahren.",
            "start": 29.66,
            "end": 30.58,
            "confidence": "0.9217789",
            "punctuated_word": "erfahren."
        },
        {
            "word": "Link",
            "start": 30.9,
            "end": 31.42,
            "confidence": "0.9652457",
            "punctuated_word": "Link"
        },
        {
            "word": "in",
            "start": 31.44,
            "end": 31.8,
            "confidence": "0.9351145",
            "punctuated_word": "in"
        },
        {
            "word": "der",
            "start": 31.82,
            "end": 32.26,
            "confidence": "0.9948663",
            "punctuated_word": "der"
        },
        {
            "word": "Bio.",
            "start": 32.28,
            "end": 32.8,
            "confidence": "0.9018870",
            "punctuated_word": "Bio."
        }
    ]
}
